{"stats":{"minecraft:broken":{"onlyhammersandexcavators:stone_excavator":2},"minecraft:mined":{"jeg:scrap_ore":4,"minecraft:sweet_berry_bush":18,"minecraft:crafting_table":1,"minecraft:glow_lichen":1,"minecraft:grass":64,"minecraft:grass_block":743,"minecraft:coal_ore":44,"ecologics:walnut_leaves":2,"minecraft:chest":1,"minecraft:sunflower":2,"minecraft:dirt":928,"minecraft:copper_ore":9,"minecraft:tall_grass":15,"minecraft:bamboo":8,"ecologics:walnut_log":4,"minecraft:stone":160,"minecraft:blue_bed":1},"minecraft:picked_up":{"minecraft:stick":3,"minecraft:crafting_table":1,"ecologics:walnut":5,"minecraft:azure_bluet":1,"ecologics:walnut_log":4,"minecraft:sweet_berries":42,"minecraft:dandelion":6,"minecraft:cornflower":1,"jeg:scrap":7,"minecraft:dirt":1651,"minecraft:blue_bed":1,"minecraft:raw_copper":27,"ecologics:walnut_sapling":3,"immersiveengineering:seed":24,"minecraft:wheat_seeds":47,"minecraft:poppy":2,"minecraft:bamboo":71,"minecraft:chest":1,"jeg:tech_trash":1,"minecraft:coal":44,"minecraft:oxeye_daisy":2,"minecraft:cobblestone":160,"minecraft:sunflower":16},"minecraft:used":{"minecraft:stone_sword":1,"minecraft:command_block":8,"minecraft:chest":1,"minecraft:wooden_pickaxe":22,"minecraft:stone":2,"minecraft:redstone_block":1,"onlyhammersandexcavators:stone_hammer":226,"minecraft:blue_bed":1,"minecraft:bedrock":137,"minecraft:torch":10,"minecraft:dirt":8,"minecraft:sweet_berries":36,"minecraft:crafting_table":1,"onlyhammersandexcavators:stone_excavator":1919,"minecraft:furnace":1,"hamsters:hamster":2},"minecraft:custom":{"minecraft:time_since_rest":8120,"minecraft:interact_with_furnace":1,"minecraft:sprint_one_cm":98110,"minecraft:damage_taken":120,"minecraft:walk_one_cm":115254,"minecraft:interact_with_crafting_table":6,"minecraft:fly_one_cm":133998,"minecraft:open_chest":3,"minecraft:crouch_one_cm":251,"minecraft:play_time":59875,"minecraft:sneak_time":507,"minecraft:jump":641,"minecraft:leave_game":2,"minecraft:time_since_death":59875,"minecraft:sleep_in_bed":3,"minecraft:total_world_time":59875,"minecraft:fall_one_cm":18202},"minecraft:crafted":{"minecraft:spruce_planks":20,"minecraft:stick":32,"onlyhammersandexcavators:stone_excavator":4,"minecraft:wooden_pickaxe":1,"minecraft:stone_sword":1,"minecraft:furnace":1,"onlyhammersandexcavators:stone_hammer":4}},"DataVersion":3465}